[{"id":1,"last_name":"Webb","first_name":"Dorothy","email":"dwebb0@gov.uk","day":"25","month":"10","year":"1948","pic":"7433"},
{"id":2,"last_name":"Wilson","first_name":"Christina","email":"cwilson1@alexa.com","day":"29","month":"7","year":"1975","pic":"6518"},
{"id":3,"last_name":"Mills","first_name":"Katherine","email":"kmills2@scribd.com","day":"10","month":"7","year":"1990","pic":"4724"},
{"id":4,"last_name":"Phillips","first_name":"Lisa","email":"lphillips3@soundcloud.com","day":"20","month":"7","year":"1953","pic":"1852"},
{"id":5,"last_name":"Warren","first_name":"Wanda","email":"wwarren4@homestead.com","day":"26","month":"9","year":"2000","pic":"2622"},
{"id":6,"last_name":"Frazier","first_name":"Matthew","email":"mfrazier5@addthis.com","day":"23","month":"10","year":"1952","pic":"7803"},
{"id":7,"last_name":"Wallace","first_name":"Brian","email":"bwallace6@furl.net","day":"11","month":"2","year":"1975","pic":"2516"},
{"id":8,"last_name":"Flores","first_name":"Arthur","email":"aflores7@myspace.com","day":"31","month":"12","year":"1965","pic":"3168"},
{"id":9,"last_name":"Duncan","first_name":"Christina","email":"cduncan8@deviantart.com","day":"17","month":"3","year":"1992","pic":"9750"},
{"id":10,"last_name":"Garza","first_name":"Victor","email":"vgarza9@tinyurl.com","day":"11","month":"10","year":"1978","pic":"6336"},
{"id":11,"last_name":"Butler","first_name":"Robin","email":"rbutlera@usgs.gov","day":"1","month":"1","year":"1959","pic":"6603"},
{"id":12,"last_name":"Williamson","first_name":"Brian","email":"bwilliamsonb@statcounter.com","day":"13","month":"6","year":"2005","pic":"4351"},
{"id":13,"last_name":"Wright","first_name":"Mary","email":"mwrightc@squidoo.com","day":"5","month":"10","year":"1976","pic":"6931"},
{"id":14,"last_name":"Richardson","first_name":"Jennifer","email":"jrichardsond@creativecommons.org","day":"8","month":"9","year":"1949","pic":"2581"},
{"id":15,"last_name":"Russell","first_name":"Christine","email":"crusselle@amazon.com","day":"8","month":"8","year":"1972","pic":"8491"},
{"id":16,"last_name":"Mcdonald","first_name":"Barbara","email":"bmcdonaldf@google.com","day":"28","month":"4","year":"1951","pic":"2598"},
{"id":17,"last_name":"Fields","first_name":"Nicole","email":"nfieldsg@google.com","day":"24","month":"6","year":"2004","pic":"5316"},
{"id":18,"last_name":"Wallace","first_name":"Julie","email":"jwallaceh@shinystat.com","day":"14","month":"6","year":"1993","pic":"4674"},
{"id":19,"last_name":"Smith","first_name":"Janice","email":"jsmithi@lycos.com","day":"14","month":"9","year":"2004","pic":"1117"},
{"id":20,"last_name":"Little","first_name":"Victor","email":"vlittlej@mapquest.com","day":"16","month":"6","year":"1941","pic":"0613"},
{"id":21,"last_name":"Walker","first_name":"Anne","email":"awalkerk@theguardian.com","day":"5","month":"11","year":"1995","pic":"3637"},
{"id":22,"last_name":"Oliver","first_name":"Bobby","email":"boliverl@newyorker.com","day":"29","month":"3","year":"1947","pic":"2506"},
{"id":23,"last_name":"Murphy","first_name":"Anna","email":"amurphym@prnewswire.com","day":"31","month":"4","year":"1952","pic":"0826"},
{"id":24,"last_name":"Hayes","first_name":"Donna","email":"dhayesn@cyberchimps.com","day":"11","month":"12","year":"1946","pic":"5220"},
{"id":25,"last_name":"Spencer","first_name":"Angela","email":"aspencero@meetup.com","day":"26","month":"12","year":"1987","pic":"2525"},
{"id":26,"last_name":"Perry","first_name":"Beverly","email":"bperryp@com.com","day":"24","month":"4","year":"1988","pic":"9088"},
{"id":27,"last_name":"Hawkins","first_name":"James","email":"jhawkinsq@princeton.edu","day":"25","month":"9","year":"1994","pic":"0782"},
{"id":28,"last_name":"Green","first_name":"Ruth","email":"rgreenr@wikia.com","day":"7","month":"5","year":"1997","pic":"9151"},
{"id":29,"last_name":"Jones","first_name":"Timothy","email":"tjoness@miibeian.gov.cn","day":"5","month":"4","year":"1980","pic":"5313"},
{"id":30,"last_name":"Mcdonald","first_name":"Janet","email":"jmcdonaldt@twitpic.com","day":"29","month":"7","year":"1988","pic":"2501"},
{"id":31,"last_name":"Jones","first_name":"Katherine","email":"kjonesu@examiner.com","day":"3","month":"5","year":"1951","pic":"8197"},
{"id":32,"last_name":"Morris","first_name":"Charles","email":"cmorrisv@hugedomains.com","day":"7","month":"10","year":"1944","pic":"8014"},
{"id":33,"last_name":"Hanson","first_name":"Arthur","email":"ahansonw@gmpg.org","day":"26","month":"6","year":"1985","pic":"4509"},
{"id":34,"last_name":"Marshall","first_name":"Jeffrey","email":"jmarshallx@miitbeian.gov.cn","day":"8","month":"9","year":"1947","pic":"3790"},
{"id":35,"last_name":"Kelly","first_name":"Justin","email":"jkellyy@blogger.com","day":"26","month":"2","year":"1950","pic":"0556"},
{"id":36,"last_name":"Castillo","first_name":"Elizabeth","email":"ecastilloz@ask.com","day":"21","month":"6","year":"1945","pic":"7339"},
{"id":37,"last_name":"Perkins","first_name":"Roy","email":"rperkins10@google.it","day":"19","month":"9","year":"1982","pic":"1786"},
{"id":38,"last_name":"Alexander","first_name":"Lois","email":"lalexander11@weibo.com","day":"21","month":"6","year":"1965","pic":"0957"},
{"id":39,"last_name":"Wheeler","first_name":"Jennifer","email":"jwheeler12@slideshare.net","day":"20","month":"7","year":"1963","pic":"0825"},
{"id":40,"last_name":"Roberts","first_name":"Fred","email":"froberts13@cnn.com","day":"12","month":"8","year":"2002","pic":"5089"},
{"id":41,"last_name":"Long","first_name":"Benjamin","email":"blong14@narod.ru","day":"30","month":"8","year":"1974","pic":"4006"},
{"id":42,"last_name":"Perry","first_name":"Craig","email":"cperry15@squidoo.com","day":"8","month":"12","year":"1961","pic":"4994"},
{"id":43,"last_name":"Ryan","first_name":"Amy","email":"aryan16@ucoz.com","day":"3","month":"3","year":"1957","pic":"6233"},
{"id":44,"last_name":"Banks","first_name":"Raymond","email":"rbanks17@scientificamerican.com","day":"25","month":"12","year":"1987","pic":"4534"},
{"id":45,"last_name":"Carpenter","first_name":"Donald","email":"dcarpenter18@blinklist.com","day":"5","month":"7","year":"1981","pic":"8284"},
{"id":46,"last_name":"Barnes","first_name":"Patricia","email":"pbarnes19@wisc.edu","day":"14","month":"8","year":"2003","pic":"7331"},
{"id":47,"last_name":"Bowman","first_name":"Donna","email":"dbowman1a@businessinsider.com","day":"23","month":"9","year":"2003","pic":"4662"},
{"id":48,"last_name":"Murphy","first_name":"Philip","email":"pmurphy1b@phoca.cz","day":"3","month":"11","year":"1989","pic":"2327"},
{"id":49,"last_name":"Henderson","first_name":"Bobby","email":"bhenderson1c@free.fr","day":"25","month":"8","year":"1958","pic":"8533"},
{"id":50,"last_name":"Brown","first_name":"Nicole","email":"nbrown1d@dedecms.com","day":"29","month":"4","year":"1950","pic":"6790"}]